odoo/addons/crm_lead_token/CHANGELOG.md
odoo/addons/crm_lead_token/README.rst
odoo/addons/crm_lead_token/__init__.py
odoo/addons/crm_lead_token/__manifest__.py
odoo/addons/crm_lead_token/i18n/ca_ES.po
odoo/addons/crm_lead_token/i18n/en_US.po
odoo/addons/crm_lead_token/i18n/es.po
odoo/addons/crm_lead_token/models/__init__.py
odoo/addons/crm_lead_token/models/crm_lead.py
odoo/addons/crm_lead_token/static/description/icon.png
odoo/addons/crm_lead_token/static/description/icon.svg
odoo/addons/crm_lead_token/tests/__init__.py
odoo/addons/crm_lead_token/tests/test_crm_lead.py
odoo/addons/crm_lead_token/views/crm_lead_views.xml
odoo_addon_crm_lead_token-16.0.1.0.0.dist-info/METADATA
odoo_addon_crm_lead_token-16.0.1.0.0.dist-info/WHEEL
odoo_addon_crm_lead_token-16.0.1.0.0.dist-info/top_level.txt
odoo_addon_crm_lead_token-16.0.1.0.0.dist-info/RECORD
